bujo/__init__.py
bujo-1.0.5.dist-info/LICENSE.txt
bujo-1.0.5.dist-info/METADATA
bujo-1.0.5.dist-info/WHEEL
bujo-1.0.5.dist-info/entry_points.txt
bujo-1.0.5.dist-info/top_level.txt
bujo-1.0.5.dist-info/RECORD
