Metadata-Version: 2.1
Name: bujo
Version: 1.0.5
Summary: A CLI tool for tracking anything and everything
Home-page: https://github.com/oref/PyBujo.git
Author: Harry Morgan <ferovax@gmail.com>
Author-email: ferovax@gmail.com
License: UNKNOWN
Keywords: cli note diary journal note-taking bullet_journal
Platform: UNKNOWN
Classifier: Intended Audience :: Developers
Classifier: Natural Language :: English
Classifier: Programming Language :: Python :: 3.4
Requires-Dist: Click
Requires-Dist: pyyaml
Requires-Dist: pick
